TestProject1635/cli.py
TestProject1635/utils.py
TestProject1635-1.0.3.dist-info/LICENSE
TestProject1635-1.0.3.dist-info/METADATA
TestProject1635-1.0.3.dist-info/WHEEL
TestProject1635-1.0.3.dist-info/entry_points.txt
TestProject1635-1.0.3.dist-info/top_level.txt
TestProject1635-1.0.3.dist-info/RECORD
