Metadata-Version: 2.1
Name: TestProject1635
Version: 1.0.3
Summary: A Python package to get weather reports for any location.
Home-page: UNKNOWN
Author: Sadanand Prajapati
Author-email: sadanandp04@gmail.com
License: MIT
Platform: UNKNOWN
Classifier: License :: OSI Approved :: MIT License
Classifier: Programming Language :: Python :: 3
Classifier: Programming Language :: Python :: 3.7
Requires-Dist: requests
